LICENSE
MANIFEST.in
README.md
requirements.txt
setup.py
auth_signals_connector/__init__.py
auth_signals_connector/connector.py
auth_signals_connector.egg-info/PKG-INFO
auth_signals_connector.egg-info/SOURCES.txt
auth_signals_connector.egg-info/dependency_links.txt
auth_signals_connector.egg-info/requires.txt
auth_signals_connector.egg-info/top_level.txt