Metadata-Version: 1.1
Name: auth-signals-connector
Version: 0.1.0
Summary: Simple abstraction layer for django.contrib.auth.signals
Home-page: https://github.com/e0ne/auth-signals-connector
Author: Ivan Kolodyazhny
Author-email: e0ne@e0ne.info
License: The MIT License (MIT)
